fraq_nettrade_abstractions/__init__.py
fraq_nettrade_abstractions/base.py
fraq_nettrade_abstractions/debug.py
fraq_nettrade_abstractions/ttypes.py
fraq_nettrade_abstractions-0.1.5.dist-info/METADATA
fraq_nettrade_abstractions-0.1.5.dist-info/WHEEL
fraq_nettrade_abstractions-0.1.5.dist-info/top_level.txt
fraq_nettrade_abstractions-0.1.5.dist-info/RECORD
