Metadata-Version: 2.4
Name: fraq-nettrade-abstractions
Version: 0.1.5
Summary: SDK for developing trading strategies in Python for FraQ NetTrade
Home-page: https://github.com/FraQLabs/FraQ-NetTrade
Author: FraQLabs
Author-email: contact@fraqlabs.com
Keywords: trading backtesting algorithmic-trading quantitative-finance
Classifier: Development Status :: 3 - Alpha
Classifier: Intended Audience :: Developers
Classifier: Intended Audience :: Financial and Insurance Industry
Classifier: Topic :: Office/Business :: Financial :: Investment
Classifier: License :: OSI Approved :: MIT License
Classifier: Programming Language :: Python :: 3
Classifier: Programming Language :: Python :: 3.9
Classifier: Programming Language :: Python :: 3.10
Classifier: Programming Language :: Python :: 3.11
Classifier: Programming Language :: Python :: 3.12
Requires-Python: >=3.9
Provides-Extra: debug
Requires-Dist: debugpy>=1.6.0; extra == "debug"
Dynamic: author
Dynamic: author-email
Dynamic: classifier
Dynamic: description
Dynamic: description-content-type
Dynamic: home-page
Dynamic: keywords
Dynamic: provides-extra
Dynamic: requires-python
Dynamic: summary
